MANIFEST.in
README.md
setup.cfg
setup.py
OpenAPI-Specification-2.1/.git
OpenAPI-Specification-2.1/schema.json
OpenAPI-Specification-2.1/example/swagger.json
OpenAPI-Specification-2.1/example/dresses/definitions.json
OpenAPI-Specification-2.1/example/dresses/swagger.json
OpenAPI-Specification-2.1/example/shoes/definitions.json
OpenAPI-Specification-2.1/example/shoes/swagger.json
openapi21/__init__.py
openapi21/cli.py
openapi21/validator.py
openapi21/version.py
openapi21.egg-info/PKG-INFO
openapi21.egg-info/SOURCES.txt
openapi21.egg-info/dependency_links.txt
openapi21.egg-info/entry_points.txt
openapi21.egg-info/requires.txt
openapi21.egg-info/top_level.txt
openapi21/spec/schema.json
openapi21/spec/schemaDefinitions/definitions.json
openapi21/spec/schemaDefinitions/responseHeadersDefinition.json
openapi21/spec/schemaDefinitions/responseHeadersObjectDefinition.json
openapi21/spec/schemaDefinitions/responsesDefinition.json
openapi21/spec/schemaDefinitions/schemaDefinition.json
openapi21/spec/schemaDefinitions/securityDefinitions.json
openapi21/spec/schemaDefinitions/parameters/bodyDefinition.json
openapi21/spec/schemaDefinitions/parameters/commonPropertiesDefinition.json
openapi21/spec/schemaDefinitions/parameters/formDataDefinition.json
openapi21/spec/schemaDefinitions/parameters/formDataObjectDefinition.json
openapi21/spec/schemaDefinitions/parameters/headerDefinition.json
openapi21/spec/schemaDefinitions/parameters/headerObjectDefinition.json
openapi21/spec/schemaDefinitions/parameters/nonBodyDefinition.json
openapi21/spec/schemaDefinitions/parameters/pathDefinition.json
openapi21/spec/schemaDefinitions/parameters/pathObjectDefinition.json
openapi21/spec/schemaDefinitions/parameters/queryDefinition.json
openapi21/spec/schemaDefinitions/parameters/queryObjectDefinition.json