Metadata-Version: 1.1
Name: openapi21
Version: 0.5.1
Summary: An Unofficial OpenAPI 2.1 Specification Python Validator
Home-page: https://github.com/dutradda/openapi21-python
Author: Diogo Dutra
Author-email: dutradda@gmail.com
License: MIT
Keywords: openapi oai swagger rest api validator validation
Platform: UNKNOWN
Classifier: License :: OSI Approved :: MIT License
Classifier: Programming Language :: Python
Classifier: Programming Language :: Python :: 2.7
Classifier: Programming Language :: Python :: 3.4
Classifier: Programming Language :: Python :: 3.5
Classifier: Programming Language :: Python :: 3.6
Classifier: Development Status :: 3 - Alpha
Classifier: Intended Audience :: Developers
Classifier: Operating System :: OS Independent
Classifier: Topic :: Internet :: WWW/HTTP
Classifier: Topic :: Software Development :: Libraries :: Python Modules
Classifier: Topic :: Utilities
Classifier: Topic :: Text Processing
